{
  "testname": "move",
  "playerNumber": 1,
  "playerNames": [
    "testName"
  ],
  "settlerNumber": 1,
  "ufosNumer": 1,
  "asteroidNumber": 23,
  "range": 1000,
  "maxRound": 22,
  "sunFlairInEveryXRound": 10,
  "homeCapacity": 5,
  "settlerCapacity": 10,
  "defOfCloseToSun": 500,
  "maxNeighbourDistance": 500,
  "realCommandQueue": [
    "0",
    "temp11",
    "assert"
  ],
  "expectedOut": [
    "GameController - player: _testName_ is on move",
    "Settler - doAction called",
    "Entity - move called",
    "Entity - listMyNeighbours called",
    "Entity - Possible neighbour: exampleInfo",
    "Settler - ChooseNeighbour called",
    "SteppableSpaceObject - checkOut called",
    "SteppableSpaceObject - checkIn called"
  ]
}